{
    "kind": "collectionType",
    "collectionName": "actividades_subgerencias",
    "info": {
        "singularName": "actividades-subgerencia",
        "pluralName": "actividades-subgerencias",
        "displayName": "Actividades Subgerencia"
    },
    "options": {
        "draftAndPublish": true
    },
    "pluginOptions": {},
    "attributes": {
        "subgerencia": {
            "type": "relation",
            "relation": "manyToOne",
            "target": "api::subgerencia.subgerencia",
            "inversedBy": "actividades_subgerencias"
        },
        "descripcion": {
            "type": "text"
        }
    }
}
